LICENSE
pyproject.toml
.github/README.md
benchcraft/__init__.py
benchcraft/entrypoint.py
benchcraft/server.py
benchcraft/agents/__init__.py
benchcraft/agents/multiple_choice.py
benchcraft/static/create.js
benchcraft/static/review.js
benchcraft/static/run.js
benchcraft/templates/base.html
benchcraft/www/__init__.py
benchcraft/www/api/__init__.py
benchcraft/www/api/api.py
benchcraft/www/create/__init__.py
benchcraft/www/create/create.py
benchcraft/www/create/templates/create.html
benchcraft/www/review/__init__.py
benchcraft/www/review/review.py
benchcraft/www/review/templates/review.html
benchcraft/www/run/__init__.py
benchcraft/www/run/run.py
benchcraft/www/run/templates/run.html
benchcraft-0.0.3.dist-info/METADATA
benchcraft-0.0.3.dist-info/WHEEL
benchcraft-0.0.3.dist-info/entry_points.txt
benchcraft-0.0.3.dist-info/licenses/LICENSE
benchcraft-0.0.3.dist-info/RECORD
