Metadata-Version: 2.4
Name: benchcraft
Version: 0.0.3
Summary: Craft and run benchmarks.
License-Expression: MIT
License-File: LICENSE
Classifier: Development Status :: 1 - Planning
Classifier: Environment :: Console
Classifier: Programming Language :: Python :: 3
Requires-Python: >=3.10
Requires-Dist: asyncio
Requires-Dist: flask
Requires-Dist: openai
Requires-Dist: sqlalchemy
Requires-Dist: tqdm
Provides-Extra: developer
Requires-Dist: bandit[toml]; extra == 'developer'
Requires-Dist: black; extra == 'developer'
Requires-Dist: hatch; extra == 'developer'
Requires-Dist: mypy; extra == 'developer'
Requires-Dist: pytest; extra == 'developer'
Requires-Dist: pytest-cov; extra == 'developer'
Requires-Dist: ruff; extra == 'developer'
